zalo_bot/__init__.py
zalo_bot/_bot.py
zalo_bot/_chat.py
zalo_bot/_link_preview_options.py
zalo_bot/_message.py
zalo_bot/_message_entity.py
zalo_bot/_update.py
zalo_bot/_user.py
zalo_bot/_version.py
zalo_bot/_webhook.py
zalo_bot/_zalo_object.py
zalo_bot/constants.py
zalo_bot/error.py
zalo_bot/updater.py
zalo_bot/warnings.py
zalo_bot/_files/__init__.py
zalo_bot/_files/_base_medium.py
zalo_bot/_files/_base_thumbed_medium.py
zalo_bot/_files/animation.py
zalo_bot/_files/audio.py
zalo_bot/_files/document.py
zalo_bot/_files/file.py
zalo_bot/_files/input_file.py
zalo_bot/_files/input_media.py
zalo_bot/_files/input_sticker.py
zalo_bot/_files/photo_size.py
zalo_bot/_files/sticker.py
zalo_bot/_files/video.py
zalo_bot/_passport/__init__.py
zalo_bot/_passport/credentials.py
zalo_bot/_utils/__init__.py
zalo_bot/_utils/argument_parsing.py
zalo_bot/_utils/datetime.py
zalo_bot/_utils/default_value.py
zalo_bot/_utils/enum.py
zalo_bot/_utils/files.py
zalo_bot/_utils/logging.py
zalo_bot/_utils/repr.py
zalo_bot/_utils/strings.py
zalo_bot/_utils/types.py
zalo_bot/_utils/warnings.py
zalo_bot/ext/__init__.py
zalo_bot/ext/_application.py
zalo_bot/ext/_context.py
zalo_bot/ext/_dispatcher.py
zalo_bot/ext/_handler.py
zalo_bot/ext/filters.py
zalo_bot/request/__init__.py
zalo_bot/request/_base_request.py
zalo_bot/request/_httpx_request.py
zalo_bot/request/_request_data.py
zalo_bot/request/_request_parameter.py
python_zalo_bot-0.1.5.dist-info/LICENSE
python_zalo_bot-0.1.5.dist-info/METADATA
python_zalo_bot-0.1.5.dist-info/WHEEL
python_zalo_bot-0.1.5.dist-info/top_level.txt
python_zalo_bot-0.1.5.dist-info/RECORD
