Metadata-Version: 2.1
Name: python-zalo-bot
Version: 0.1.5
Summary: A simple library for Zalo Bot API
Author-email: ZTP <your_email@example.com>
License: MIT
Project-URL: Homepage, https://github.com/yourusername/python-zalo-bot
Project-URL: Issues, https://github.com/yourusername/python-zalo-bot/issues
Requires-Python: >=3.8
License-File: LICENSE
